napari_labelprop/__init__.py
napari_labelprop/_label_prop_widget.py
napari_labelprop/_reader.py
napari_labelprop/_sample_data.py
napari_labelprop/_widget.py
napari_labelprop/_writer.py
napari_labelprop/napari.yaml
napari_labelprop/_tests/__init__.py
napari_labelprop/_tests/test_sample_data.py
napari_labelprop/_tests/test_widget.py
napari_labelprop-1.0.0.dist-info/LICENSE
napari_labelprop-1.0.0.dist-info/METADATA
napari_labelprop-1.0.0.dist-info/WHEEL
napari_labelprop-1.0.0.dist-info/entry_points.txt
napari_labelprop-1.0.0.dist-info/top_level.txt
napari_labelprop-1.0.0.dist-info/RECORD
